image_slicer/__init__.py
image_slicer/cli.py
image_slicer/join_cli.py
image_slicer/slicer.py
image_slicer-3.1.0.dist-info/METADATA
image_slicer-3.1.0.dist-info/WHEEL
image_slicer-3.1.0.dist-info/entry_points.txt
image_slicer-3.1.0.dist-info/licenses/LICENSE
image_slicer-3.1.0.dist-info/RECORD
