Metadata-Version: 2.4
Name: image-slicer
Version: 3.1.0
Summary: A high-performance Python library to slice images into tiles.
Project-URL: Homepage, https://github.com/samdobson/image_slicer
Project-URL: Repository, https://github.com/samdobson/image_slicer
Author-email: Sam Dobson <1309834+samdobson@users.noreply.github.com>
License: MIT
License-File: LICENSE
Classifier: Development Status :: 5 - Production/Stable
Classifier: Intended Audience :: Developers
Classifier: License :: OSI Approved :: MIT License
Classifier: Programming Language :: Python :: 3
Classifier: Programming Language :: Python :: 3.8
Classifier: Programming Language :: Python :: 3.9
Classifier: Programming Language :: Python :: 3.10
Classifier: Programming Language :: Python :: 3.11
Classifier: Programming Language :: Python :: 3.12
Classifier: Programming Language :: Python :: 3.13
Classifier: Topic :: Multimedia :: Graphics :: Graphics Conversion
Classifier: Topic :: Software Development :: Libraries :: Python Modules
Requires-Python: >=3.8
Requires-Dist: pyvips[binary]
Provides-Extra: dev
Requires-Dist: black; extra == 'dev'
Requires-Dist: coveralls; extra == 'dev'
Requires-Dist: mkdocs; extra == 'dev'
Requires-Dist: mkdocs-material; extra == 'dev'
Requires-Dist: pillow; extra == 'dev'
Requires-Dist: pyre-check; extra == 'dev'
Requires-Dist: pytest; extra == 'dev'
Requires-Dist: pytest-cov; extra == 'dev'
Requires-Dist: ruff; extra == 'dev'
Requires-Dist: tox; extra == 'dev'
